mlship/__init__.py
mlship/benchmark.py
mlship/cli.py
mlship/errors.py
mlship/models.py
mlship/pipeline.py
mlship/server.py
mlship/utils.py
mlship/loaders/__init__.py
mlship/loaders/base.py
mlship/loaders/detector.py
mlship/loaders/huggingface.py
mlship/loaders/pytorch.py
mlship/loaders/sklearn.py
mlship/loaders/tensorflow.py
mlship-0.2.0.dist-info/licenses/LICENSE
mlship-0.2.0.dist-info/METADATA
mlship-0.2.0.dist-info/WHEEL
mlship-0.2.0.dist-info/entry_points.txt
mlship-0.2.0.dist-info/top_level.txt
mlship-0.2.0.dist-info/RECORD
