Metadata-Version: 2.4
Name: mlship
Version: 0.2.0
Summary: Turn ML models into APIs with one command
Author-email: Sudhanva Labs <contact@sudhanvalabs.com>
License: MIT
Project-URL: Homepage, https://github.com/sudhanvalabs/mlship
Project-URL: Documentation, https://github.com/sudhanvalabs/mlship#readme
Project-URL: Repository, https://github.com/sudhanvalabs/mlship
Project-URL: Issues, https://github.com/sudhanvalabs/mlship/issues
Keywords: machine-learning,api,deployment,fastapi,ml,model-serving
Classifier: Development Status :: 3 - Alpha
Classifier: Intended Audience :: Developers
Classifier: Intended Audience :: Education
Classifier: Intended Audience :: Science/Research
Classifier: License :: OSI Approved :: MIT License
Classifier: Programming Language :: Python :: 3
Classifier: Programming Language :: Python :: 3.11
Classifier: Programming Language :: Python :: 3.12
Classifier: Topic :: Scientific/Engineering :: Artificial Intelligence
Classifier: Topic :: Software Development :: Libraries :: Python Modules
Requires-Python: <3.13,>=3.11
License-File: LICENSE
Requires-Dist: click>=8.0
Requires-Dist: fastapi>=0.104
Requires-Dist: uvicorn[standard]>=0.24
Requires-Dist: pydantic>=2.0
Requires-Dist: python-multipart>=0.0.6
Requires-Dist: requests>=2.31
Provides-Extra: sklearn
Requires-Dist: scikit-learn>=1.0; extra == "sklearn"
Requires-Dist: joblib>=1.0; extra == "sklearn"
Provides-Extra: pytorch
Requires-Dist: torch>=2.0; extra == "pytorch"
Provides-Extra: tensorflow
Requires-Dist: tensorflow>=2.13; extra == "tensorflow"
Requires-Dist: tf-keras>=2.16; extra == "tensorflow"
Provides-Extra: xgboost
Requires-Dist: xgboost>=2.0; extra == "xgboost"
Provides-Extra: lightgbm
Requires-Dist: lightgbm>=4.0; extra == "lightgbm"
Provides-Extra: huggingface
Requires-Dist: transformers>=4.30; extra == "huggingface"
Requires-Dist: torch>=2.0; extra == "huggingface"
Requires-Dist: tf-keras>=2.16; extra == "huggingface"
Provides-Extra: all
Requires-Dist: scikit-learn>=1.0; extra == "all"
Requires-Dist: joblib>=1.0; extra == "all"
Requires-Dist: torch>=2.0; extra == "all"
Requires-Dist: tensorflow>=2.13; extra == "all"
Requires-Dist: tf-keras>=2.16; extra == "all"
Requires-Dist: xgboost>=2.0; extra == "all"
Requires-Dist: lightgbm>=4.0; extra == "all"
Requires-Dist: transformers>=4.30; extra == "all"
Provides-Extra: dev
Requires-Dist: pytest>=7.0; extra == "dev"
Requires-Dist: pytest-cov>=4.0; extra == "dev"
Requires-Dist: black>=23.0; extra == "dev"
Requires-Dist: mypy>=1.0; extra == "dev"
Requires-Dist: ruff>=0.1; extra == "dev"
Requires-Dist: httpx>=0.25; extra == "dev"
Dynamic: license-file
